krayt/__about__.py
krayt/__init__.py
krayt/bundles.py
krayt/package.py
krayt/templates.py
krayt/cli/__init__.py
krayt/cli/bundles.py
krayt/cli/pod.py
krayt/cli/templates.py
krayt/templates/.kraytrc
krayt/templates/base.sh
krayt/templates/install.sh
krayt/templates/kraytrc.sh
krayt/templates/motd.sh
krayt-0.4.3.dist-info/METADATA
krayt-0.4.3.dist-info/WHEEL
krayt-0.4.3.dist-info/entry_points.txt
krayt-0.4.3.dist-info/licenses/LICENSE
krayt-0.4.3.dist-info/RECORD
