Metadata-Version: 2.4
Name: krayt
Version: 0.4.3
Summary: kubernetes volume explorer
Project-URL: Homepage, https://github.com/waylonwalker/krayt#readme
Project-URL: Documentation, https://github.com/waylonwalker/krayt#readme
Project-URL: Changelog, https://github.com/waylonwalker/krayt#changelog
Project-URL: Issues, https://github.com/waylonwalker/krayt/issues
Project-URL: Source, https://github.com/waylonwalker/krayt
Author-email: Waylon Walker <waylon@waylonwalker.com>
License: MIT License
License-File: LICENSE
Classifier: Development Status :: 4 - Beta
Classifier: Programming Language :: Python
Classifier: Programming Language :: Python :: 3.8
Classifier: Programming Language :: Python :: 3.9
Classifier: Programming Language :: Python :: 3.10
Classifier: Programming Language :: Python :: 3.11
Classifier: Programming Language :: Python :: 3.12
Classifier: Programming Language :: Python :: Implementation :: CPython
Classifier: Programming Language :: Python :: Implementation :: PyPy
Requires-Python: >=3.8
Requires-Dist: inquirer
Requires-Dist: inquirerpy
Requires-Dist: iterfzf
Requires-Dist: jinja2
Requires-Dist: kubernetes
Requires-Dist: more-itertools
Requires-Dist: pydantic
Requires-Dist: typer
